{
    "uid": "4f6d6afd-46bf-4393-801e-8f8330c366bf",
    "name": "28_CatBoost",
    "preprocessing": [
        {
            "scale_y": {
                "scale": [
                    372.40060280265976
                ],
                "mean": [
                    587.7025641025641
                ],
                "var": [
                    138682.20896778436
                ],
                "n_samples_seen": 195,
                "n_features_in": 1,
                "columns": [
                    "target"
                ],
                "scale_method": "scale_normal"
            },
            "ml_task": "regression",
            "params": {
                "columns_preprocessing": {},
                "target_preprocessing": [
                    "na_exclude",
                    "scale_normal"
                ],
                "ml_task": "regression"
            }
        },
        {
            "scale_y": {
                "scale": [
                    372.2690516784961
                ],
                "mean": [
                    588.2666666666667
                ],
                "var": [
                    138584.24683760683
                ],
                "n_samples_seen": 195,
                "n_features_in": 1,
                "columns": [
                    "target"
                ],
                "scale_method": "scale_normal"
            },
            "ml_task": "regression",
            "params": {
                "columns_preprocessing": {},
                "target_preprocessing": [
                    "na_exclude",
                    "scale_normal"
                ],
                "ml_task": "regression"
            }
        },
        {
            "scale_y": {
                "scale": [
                    364.48422524664755
                ],
                "mean": [
                    580.2923076923076
                ],
                "var": [
                    132848.7504536489
                ],
                "n_samples_seen": 195,
                "n_features_in": 1,
                "columns": [
                    "target"
                ],
                "scale_method": "scale_normal"
            },
            "ml_task": "regression",
            "params": {
                "columns_preprocessing": {},
                "target_preprocessing": [
                    "na_exclude",
                    "scale_normal"
                ],
                "ml_task": "regression"
            }
        },
        {
            "scale_y": {
                "scale": [
                    377.1105779580964
                ],
                "mean": [
                    581.3384615384615
                ],
                "var": [
                    142212.38800788953
                ],
                "n_samples_seen": 195,
                "n_features_in": 1,
                "columns": [
                    "target"
                ],
                "scale_method": "scale_normal"
            },
            "ml_task": "regression",
            "params": {
                "columns_preprocessing": {},
                "target_preprocessing": [
                    "na_exclude",
                    "scale_normal"
                ],
                "ml_task": "regression"
            }
        },
        {
            "scale_y": {
                "scale": [
                    370.8276392981945
                ],
                "mean": [
                    591.8775510204082
                ],
                "var": [
                    137513.13806747188
                ],
                "n_samples_seen": 196,
                "n_features_in": 1,
                "columns": [
                    "target"
                ],
                "scale_method": "scale_normal"
            },
            "ml_task": "regression",
            "params": {
                "columns_preprocessing": {},
                "target_preprocessing": [
                    "na_exclude",
                    "scale_normal"
                ],
                "ml_task": "regression"
            }
        }
    ],
    "learners": [
        {
            "library_version": "1.2.7",
            "algorithm_name": "CatBoost",
            "algorithm_short_name": "CatBoost",
            "uid": "8e8ee0e3-d4bb-4e2e-b1bf-dc3b2ca6e989",
            "params": {
                "model_type": "CatBoost",
                "ml_task": "regression",
                "n_jobs": -1,
                "learning_rate": 0.1,
                "depth": 7,
                "rsm": 1,
                "loss_function": "RMSE",
                "seed": 4,
                "eval_metric": "RMSE",
                "explain_level": 1
            },
            "name": "learner_fold_0",
            "best_ntree_limit": 45
        },
        {
            "library_version": "1.2.7",
            "algorithm_name": "CatBoost",
            "algorithm_short_name": "CatBoost",
            "uid": "c4c51f0f-7098-43ae-a464-6f0033ca28e6",
            "params": {
                "model_type": "CatBoost",
                "ml_task": "regression",
                "n_jobs": -1,
                "learning_rate": 0.1,
                "depth": 7,
                "rsm": 1,
                "loss_function": "RMSE",
                "seed": 4,
                "eval_metric": "RMSE",
                "explain_level": 1
            },
            "name": "learner_fold_1",
            "best_ntree_limit": 87
        },
        {
            "library_version": "1.2.7",
            "algorithm_name": "CatBoost",
            "algorithm_short_name": "CatBoost",
            "uid": "056243c9-39f3-4d32-b1f0-68ec8de11981",
            "params": {
                "model_type": "CatBoost",
                "ml_task": "regression",
                "n_jobs": -1,
                "learning_rate": 0.1,
                "depth": 7,
                "rsm": 1,
                "loss_function": "RMSE",
                "seed": 4,
                "eval_metric": "RMSE",
                "explain_level": 1
            },
            "name": "learner_fold_2",
            "best_ntree_limit": 185
        },
        {
            "library_version": "1.2.7",
            "algorithm_name": "CatBoost",
            "algorithm_short_name": "CatBoost",
            "uid": "ee7cbd3a-2436-4b48-a783-903c0860fdbc",
            "params": {
                "model_type": "CatBoost",
                "ml_task": "regression",
                "n_jobs": -1,
                "learning_rate": 0.1,
                "depth": 7,
                "rsm": 1,
                "loss_function": "RMSE",
                "seed": 4,
                "eval_metric": "RMSE",
                "explain_level": 1
            },
            "name": "learner_fold_3",
            "best_ntree_limit": 205
        },
        {
            "library_version": "1.2.7",
            "algorithm_name": "CatBoost",
            "algorithm_short_name": "CatBoost",
            "uid": "02c1c243-09ef-4ffc-839b-ad1497c82fcd",
            "params": {
                "model_type": "CatBoost",
                "ml_task": "regression",
                "n_jobs": -1,
                "learning_rate": 0.1,
                "depth": 7,
                "rsm": 1,
                "loss_function": "RMSE",
                "seed": 4,
                "eval_metric": "RMSE",
                "explain_level": 1
            },
            "name": "learner_fold_4",
            "best_ntree_limit": 57
        }
    ],
    "params": {
        "additional": {
            "max_rounds": 10000,
            "early_stopping_rounds": 50,
            "max_rows_limit": null,
            "max_cols_limit": null
        },
        "preprocessing": {
            "columns_preprocessing": {},
            "target_preprocessing": [
                "na_exclude",
                "scale_normal"
            ],
            "ml_task": "regression"
        },
        "validation_strategy": {
            "validation_type": "kfold",
            "k_folds": 5,
            "shuffle": true,
            "X_path": "AutoML_2\\X.data",
            "y_path": "AutoML_2\\y.data",
            "results_path": "AutoML_2"
        },
        "learner": {
            "model_type": "CatBoost",
            "ml_task": "regression",
            "n_jobs": -1,
            "learning_rate": 0.1,
            "depth": 7,
            "rsm": 1,
            "loss_function": "RMSE",
            "seed": 4,
            "eval_metric": "RMSE",
            "explain_level": 1
        },
        "automl_random_state": 1234,
        "ml_task": "regression",
        "explain_level": 1,
        "name": "28_CatBoost",
        "status": "initialized",
        "final_loss": null,
        "train_time": null,
        "data_type": "original",
        "max_time_for_learner": 60
    },
    "saved": [
        "28_CatBoost\\learner_fold_0.catboost",
        "28_CatBoost\\learner_fold_1.catboost",
        "28_CatBoost\\learner_fold_2.catboost",
        "28_CatBoost\\learner_fold_3.catboost",
        "28_CatBoost\\learner_fold_4.catboost"
    ],
    "predictions_fname": "28_CatBoost\\predictions_out_of_folds.csv",
    "metric_name": "rmse",
    "final_loss": "184.0547131278346",
    "train_time": 18.36714744567871,
    "is_stacked": false,
    "joblib_version": "1.4.2",
    "single_prediction_time": 0.023000001907348633
}